flowmapper/__init__.py
flowmapper/cas.py
flowmapper/cli.py
flowmapper/constants.py
flowmapper/context.py
flowmapper/errors.py
flowmapper/flow.py
flowmapper/flowmap.py
flowmapper/main.py
flowmapper/match.py
flowmapper/string_field.py
flowmapper/string_list.py
flowmapper/transformation_mapping.py
flowmapper/unit.py
flowmapper/utils.py
flowmapper/data/manual_name_match_simapro_ecoinvent_3.8.json
flowmapper/data/manual_name_match_simapro_ecoinvent_3.9.json
flowmapper/data/names_and_locations.json
flowmapper/data/places.json
flowmapper/data/simapro-2023-ecoinvent-3-contexts.json
flowmapper/data/standard-units-harmonization.json
flowmapper/data/units.txt
flowmapper/extraction/__init__.py
flowmapper/extraction/ecospold2.py
flowmapper/extraction/simapro_csv.py
flowmapper/extraction/simapro_ecospold1.py
flowmapper/manual_matching/simapro_ecoinvent_310.py
flowmapper/manual_matching/data/simapro_ecoinvent_310/just_different.json
flowmapper/manual_matching/data/simapro_ecoinvent_310/land_use_not_in_ecoinvent.json
flowmapper/manual_matching/data/simapro_ecoinvent_310/regionalized_random.json
flowmapper/manual_matching/data/simapro_ecoinvent_310/unit_conversions.json
flowmapper/manual_matching/data/simapro_ecoinvent_310/water_misc.json
flowmapper/manual_matching/results/simapro-2024-ecoinvent-3.10-biosphere.json
flowmapper-0.4.dist-info/LICENSE
flowmapper-0.4.dist-info/METADATA
flowmapper-0.4.dist-info/WHEEL
flowmapper-0.4.dist-info/entry_points.txt
flowmapper-0.4.dist-info/top_level.txt
flowmapper-0.4.dist-info/RECORD
