Metadata-Version: 2.2
Name: flowmapper
Version: 0.4
Summary: Generate mappings between elementary flow lists
Author-email: Francisco Alves de Oliveira Júnior <fjunior.alves.oliveira@gmail.com>, Chris Mute <cmutel@gmail.com>
Maintainer-email: Chris Mute <cmutel@gmail.com>
Project-URL: source, https://github.com/cmutel/flowmapper
Project-URL: homepage, https://github.com/cmutel/flowmapper
Project-URL: tracker, https://github.com/cmutel/flowmapper/issues
Classifier: Development Status :: 4 - Beta
Classifier: Programming Language :: Python
Classifier: Programming Language :: Python :: 3
Classifier: Programming Language :: Python :: 3.9
Classifier: Programming Language :: Python :: 3.10
Classifier: Programming Language :: Python :: 3.11
Classifier: Programming Language :: Python :: 3.12
Classifier: Natural Language :: English
Classifier: Operating System :: OS Independent
Classifier: Topic :: Scientific/Engineering
Requires-Python: >=3.10
License-File: LICENSE
Requires-Dist: bw_simapro_csv
Requires-Dist: pandas[excel]
Requires-Dist: pint
Requires-Dist: pydantic
Requires-Dist: pyecospold
Requires-Dist: randonneur>=0.6
Requires-Dist: randonneur_data
Requires-Dist: tqdm
Requires-Dist: typer
Requires-Dist: xmltodict
Provides-Extra: testing
Requires-Dist: flowmapper; extra == "testing"
Requires-Dist: pytest; extra == "testing"
Requires-Dist: pytest-cov; extra == "testing"
Requires-Dist: python-coveralls; extra == "testing"
Requires-Dist: deepdiff; extra == "testing"
Provides-Extra: dev
Requires-Dist: build; extra == "dev"
Requires-Dist: pre-commit; extra == "dev"
Requires-Dist: pylint; extra == "dev"
Requires-Dist: pytest; extra == "dev"
Requires-Dist: pytest-cov; extra == "dev"
Requires-Dist: setuptools; extra == "dev"
